pytest_adf/__init__.py
pytest_adf/pytest_adf.py
pytest_adf-0.1.5.dist-info/LICENSE
pytest_adf-0.1.5.dist-info/METADATA
pytest_adf-0.1.5.dist-info/WHEEL
pytest_adf-0.1.5.dist-info/entry_points.txt
pytest_adf-0.1.5.dist-info/top_level.txt
pytest_adf-0.1.5.dist-info/RECORD
